probing_environments/adaptors/rlberry.py
probing_environments/adaptors/sb3.py
probing_environments/adaptors/template.py
probing_environments/checks.py
probing_environments/envs.py
probing_environments/utils/type_hints.py
probing_environments-0.4.0.dist-info/LICENSE
probing_environments-0.4.0.dist-info/METADATA
probing_environments-0.4.0.dist-info/WHEEL
probing_environments-0.4.0.dist-info/RECORD
