Metadata-Version: 2.1
Name: probing-environments
Version: 0.4.0
Summary: Probing environments for RL/DeepRL algorithms debugging
Author: Yann Berthelot
Author-email: yannberthelot1@gmail.com
Requires-Python: >=3.8,<4.0
Classifier: Programming Language :: Python :: 3
Classifier: Programming Language :: Python :: 3.8
Classifier: Programming Language :: Python :: 3.9
Classifier: Programming Language :: Python :: 3.10
Classifier: Programming Language :: Python :: 3.11
Requires-Dist: gymnasium (>=0.28.1,<0.29.0)
Requires-Dist: mypy-extensions (>=1.0.0,<2.0.0)
Requires-Dist: pytest (>=7.4.0,<8.0.0)
